{
  "others": {
    "1.抽獎機率如何算？": [
      "公式：獎項/總籤數=機率%",
      "以總籤數80抽為例，若A賞在此套標註為2/2，表示這套A賞在80抽內有2抽為A賞。以「A賞」2抽除以「總籤數」80抽可以得到一抽的概率為2.5%，A賞的概率為2.5%。",
      "若總籤數56抽為例，A賞在此套標註為½（如下圖一）所示，表示這套A賞在56抽內有1抽為A賞。以「A賞」1抽除以「總籤數」56抽可以得到一抽的概率為1.8%，A賞的概率為1.8%。",
      {
        "imgSrc": "drawProbability/1.png"
      },
      "此平台的每一套籤數與大獎數量皆不同，且會依照顧客的消費導致總籤數及大獎數量的浮動，在購買前請先確定「大獎」的機率符合您的期望值。"
    ],
    "2.如何查看此套商品的總籤數？": [
      "在平台的頁面上可以查看左下角（如下圖所示），左下角所示為56/80抽，56數字為顧客有消費導致總籤數原本為80抽下降至56抽；80數字為此套商品的總籤數為80張。",
      {
        "imgSrc": "drawProbability/2.png"
      }
    ],
    "3.如何查看大獎的剩餘數量？": [
      "選好商品進入後在「下單前須知」下方有可左右滑動的賞品展示，可提供顧客方便知道大獎的剩餘數量。"
    ]
  }
}